LICENSE
MANIFEST.in
README.rst
setup.py
tbgrep/__init__.py
tbgrep/commands.py
tbgrep.egg-info/PKG-INFO
tbgrep.egg-info/SOURCES.txt
tbgrep.egg-info/dependency_links.txt
tbgrep.egg-info/entry_points.txt
tbgrep.egg-info/not-zip-safe
tbgrep.egg-info/top_level.txt