Metadata-Version: 1.1
Name: tbgrep
Version: 0.2.3
Summary: Extract Python Tracebacks from text
Home-page: http://github.com/lmacken/tbgrep
Author: Luke Macken
Author-email: lmacken@redhat.com
License: GPLv3+
Platform: UNKNOWN
Classifier: Development Status :: 4 - Beta
Classifier: Environment :: Console
Classifier: Intended Audience :: Developers
Classifier: Intended Audience :: System Administrators
Classifier: License :: OSI Approved :: GNU General Public License (GPL)
Classifier: Topic :: Software Development :: Debuggers
Classifier: Topic :: Text Processing :: Filters
Classifier: Topic :: Utilities
Classifier: Topic :: Internet :: Log Analysis
Classifier: Programming Language :: Python
Classifier: Programming Language :: Python :: 3
